{
  "request": {
    "keyword": "tiny house san diego",
    "location_name": "United States",
    "language_name": "English",
    "device": "desktop",
    "os": "windows",
    "depth": 30
  },
  "response": {
    "version": "0.1.20260717",
    "status_code": 20000,
    "status_message": "Ok.",
    "time": "5.0346 sec.",
    "cost": 0.006,
    "tasks_count": 1,
    "tasks_error": 0,
    "tasks": [
      {
        "id": "07181909-2024-0139-0000-1b3d7a100403",
        "status_code": 20000,
        "status_message": "Ok.",
        "time": "4.8654 sec.",
        "cost": 0.006,
        "result_count": 1,
        "path": [
          "v3",
          "serp",
          "google",
          "organic",
          "live",
          "advanced"
        ],
        "data": {
          "api": "serp",
          "function": "live",
          "se": "google",
          "se_type": "organic",
          "keyword": "tiny house san diego",
          "location_name": "United States",
          "language_name": "English",
          "device": "desktop",
          "os": "windows",
          "depth": 30
        },
        "result": [
          {
            "keyword": "tiny house san diego",
            "type": "organic",
            "se_domain": "google.com",
            "location_code": 2840,
            "language_code": "en",
            "check_url": "https://www.google.com/search?q=tiny%20house%20san%20diego&hl=en&gl=US&ie=UTF-8&uule=w+CAIQIFISCQs2MuSEtepUEUK33kOSuTsc",
            "datetime": "2026-07-18 16:09:22 +00:00",
            "spell": null,
            "refinement_chips": null,
            "item_types": [
              "organic",
              "people_also_ask",
              "discussions_and_forums",
              "video",
              "short_videos",
              "related_searches",
              "images"
            ],
            "se_results_count": 125,
            "pages_count": 3,
            "items_count": 34,
            "items": [
              {
                "type": "organic",
                "rank_group": 1,
                "rank_absolute": 1,
                "page": 1,
                "position": "left",
                "xpath": "/html[1]/body[1]/div[3]/div[1]/div[12]/div[1]/div[2]/div[2]/div[1]/div[1]/div[1]/div[1]/div[1]",
                "domain": "tinyhouselistings.com",
                "title": "Tiny Houses For Sale In San Diego",
                "url": "https://tinyhouselistings.com/cities/San%20Diego",
                "cache_url": null,
                "related_search_url": null,
                "breadcrumb": "https://tinyhouselistings.com › cities › San Diego",
                "website_name": "Tiny House Listings",
                "is_image": false,
                "is_video": false,
                "is_featured_snippet": false,
                "is_malicious": false,
                "is_web_story": false,
                "description": "Tiny Houses For Sale in San Diego. $84,995 For Sale. Tiny House. 30' Modern 1-Bedroom Tiny House on Wheels | Main-Floor Bedroom | RV Certified. San Diego, ... Read more",
                "pre_snippet": null,
                "extended_snippet": null,
                "images": null,
                "amp_version": false,
                "rating": null,
                "price": null,
                "highlighted": [
                  "Tiny Houses For Sale in San Diego"
                ],
                "links": null,
                "faq": null,
                "extended_people_also_search": null,
                "about_this_result": null,
                "related_result": null,
                "timestamp": null,
                "rectangle": null
              },
              {
                "type": "organic",
                "rank_group": 2,
                "rank_absolute": 2,
                "page": 1,
                "position": "left",
                "xpath": "/html[1]/body[1]/div[3]/div[1]/div[12]/div[1]/div[2]/div[2]/div[1]/div[1]/div[2]/div[1]/div[1]",
                "domain": "www.zentinyhomes.com",
                "title": "San Diego's #1 Tiny Home Builder, Zen Tiny Homes",
                "url": "https://www.zentinyhomes.com/",
                "cache_url": null,
                "related_search_url": null,
                "breadcrumb": "https://www.zentinyhomes.com",
                "website_name": "zen tiny homes",
                "is_image": false,
                "is_video": false,
                "is_featured_snippet": false,
                "is_malicious": false,
                "is_web_story": false,
                "description": "Zen Tiny Homes is San Diego's #1 tiny home builder. From the ground up, we work one-on-one with our clients to expertly design and construct fully customized ... Read more",
                "pre_snippet": null,
                "extended_snippet": null,
                "images": null,
                "amp_version": false,
                "rating": null,
                "price": null,
                "highlighted": [
                  "Zen Tiny Homes is San Diego's #1 tiny home builder"
                ],
                "links": [
                  {
                    "type": "link_element",
                    "title": "Models",
                    "description": null,
                    "url": "https://www.zentinyhomes.com/models",
                    "domain": "www.zentinyhomes.com"
                  },
                  {
                    "type": "link_element",
                    "title": "Programs",
                    "description": null,
                    "url": "https://www.zentinyhomes.com/programs",
                    "domain": "www.zentinyhomes.com"
                  },
                  {
                    "type": "link_element",
                    "title": "Order",
                    "description": null,
                    "url": "https://www.zentinyhomes.com/contact",
                    "domain": "www.zentinyhomes.com"
                  },
                  {
                    "type": "link_element",
                    "title": "Blog.",
                    "description": null,
                    "url": "https://www.zentinyhomes.com/blog",
                    "domain": "www.zentinyhomes.com"
                  }
                ],
                "faq": null,
                "extended_people_also_search": null,
                "about_this_result": null,
                "related_result": null,
                "timestamp": null,
                "rectangle": null
              },
              {
                "type": "people_also_ask",
                "rank_group": 1,
                "rank_absolute": 3,
                "page": 1,
                "position": "left",
                "xpath": "/html[1]/body[1]/div[3]/div[1]/div[12]/div[1]/div[2]/div[2]/div[1]/div[1]/div[4]/div[1]/div[1]/div[1]",
                "items": [
                  {
                    "type": "people_also_ask_element",
                    "title": "Are tiny homes allowed in San Diego?",
                    "seed_question": null,
                    "xpath": "/html[1]/body[1]/div[3]/div[1]/div[12]/div[1]/div[2]/div[2]/div[1]/div[1]/div[4]/div[1]/div[1]/div[1]/div[1]/div[2]/div[1]",
                    "expanded_element": [
                      {
                        "type": "people_also_ask_ai_overview_expanded_element",
                        "items": null,
                        "references": null,
                        "asynchronous_ai_overview": true
                      }
                    ]
                  },
                  {
                    "type": "people_also_ask_element",
                    "title": "Is there a tiny house community in San Diego?",
                    "seed_question": null,
                    "xpath": "/html[1]/body[1]/div[3]/div[1]/div[12]/div[1]/div[2]/div[2]/div[1]/div[1]/div[4]/div[1]/div[1]/div[1]/div[1]/div[2]/div[2]",
                    "expanded_element": [
                      {
                        "type": "people_also_ask_ai_overview_expanded_element",
                        "items": null,
                        "references": null,
                        "asynchronous_ai_overview": true
                      }
                    ]
                  },
                  {
                    "type": "people_also_ask_element",
                    "title": "How much does a tiny house cost in San Diego?",
                    "seed_question": null,
                    "xpath": "/html[1]/body[1]/div[3]/div[1]/div[12]/div[1]/div[2]/div[2]/div[1]/div[1]/div[4]/div[1]/div[1]/div[1]/div[1]/div[2]/div[3]",
                    "expanded_element": [
                      {
                        "type": "people_also_ask_ai_overview_expanded_element",
                        "items": null,
                        "references": null,
                        "asynchronous_ai_overview": true
                      }
                    ]
                  },
                  {
                    "type": "people_also_ask_element",
                    "title": "Can I build a tiny home for $10,000?",
                    "seed_question": null,
                    "xpath": "/html[1]/body[1]/div[3]/div[1]/div[12]/div[1]/div[2]/div[2]/div[1]/div[1]/div[4]/div[1]/div[1]/div[1]/div[1]/div[2]/div[4]",
                    "expanded_element": [
                      {
                        "type": "people_also_ask_ai_overview_expanded_element",
                        "items": null,
                        "references": null,
                        "asynchronous_ai_overview": true
                      }
                    ]
                  }
                ],
                "rectangle": null
              },
              {
                "type": "discussions_and_forums",
                "rank_group": 1,
                "rank_absolute": 4,
                "page": 1,
                "position": "left",
                "xpath": "/html[1]/body[1]/div[3]/div[1]/div[12]/div[1]/div[2]/div[2]/div[1]/div[1]/div[6]/div[1]",
                "title": "Discussions and forums",
                "items": [
                  {
                    "type": "discussions_and_forums_element",
                    "title": "I want a tiny house - here in San Diego CA - any tips?",
                    "url": "https://www.reddit.com/r/TinyHouses/comments/1eqz449/i_want_a_tiny_house_here_in_san_diego_ca_any_tips/",
                    "domain": "www.reddit.com",
                    "source": "Reddit",
                    "description": null,
                    "timestamp": "2025-07-18 16:09:20 +00:00",
                    "posts_count": 20
                  },
                  {
                    "type": "discussions_and_forums_element",
                    "title": "Where to buy and install tiny homes in San Diego?",
                    "url": "https://www.facebook.com/groups/tinyhousesandiego/posts/1996418703818114/",
                    "domain": "www.facebook.com",
                    "source": "Facebook",
                    "description": null,
                    "timestamp": "2019-07-18 16:09:20 +00:00",
                    "posts_count": null
                  }
                ],
                "rectangle": null
              },
              {
                "type": "video",
                "rank_group": 1,
                "rank_absolute": 5,
                "page": 1,
                "position": "left",
                "xpath": "/html[1]/body[1]/div[3]/div[1]/div[12]/div[1]/div[2]/div[2]/div[1]/div[1]/div[8]/div[1]",
                "items": [
                  {
                    "type": "video_element",
                    "source": "Facebook · Tiny House Expedition",
                    "title": "Inside San Diego's first legal tiny house village #TinyHouse ...",
                    "timestamp": "2025-12-08 00:00:00 +00:00",
                    "url": "https://www.facebook.com/TinyHouseExpedition/videos/inside-san-diegos-first-legal-tiny-house-village/1934186710840674/"
                  },
                  {
                    "type": "video_element",
                    "source": "YouTube · NBC 7 San Diego",
                    "title": "Tiny homes roll into San Diego in hopes of combating housing ...",
                    "timestamp": "2025-10-03 00:00:00 +00:00",
                    "url": "https://www.youtube.com/watch?v=qdJ1E3iElOo"
                  },
                  {
                    "type": "video_element",
                    "source": "YouTube · Clever Tiny Homes",
                    "title": "San Diego Legalizes Tiny Homes on Wheels",
                    "timestamp": "2025-11-05 00:00:00 +00:00",
                    "url": "https://www.youtube.com/watch?v=-kopHsG8hmM"
                  }
                ],
                "rectangle": null
              },
              {
                "type": "organic",
                "rank_group": 3,
                "rank_absolute": 6,
                "page": 1,
                "position": "left",
                "xpath": "/html[1]/body[1]/div[3]/div[1]/div[12]/div[1]/div[2]/div[2]/div[1]/div[1]/div[10]/div[1]/div[1]",
                "domain": "www.countynewscenter.com",
                "title": "County Adds Tiny Homes on Wheels to Housing Options",
                "url": "https://www.countynewscenter.com/county-adds-tiny-homes-on-wheels-to-housing-options/",
                "cache_url": null,
                "related_search_url": null,
                "breadcrumb": "https://www.countynewscenter.com › county-adds-tiny-h...",
                "website_name": "San Diego County News Center",
                "is_image": false,
                "is_video": false,
                "is_featured_snippet": false,
                "is_malicious": false,
                "is_web_story": false,
                "description": "Oct 1, 2025 — A new housing option is now eligible to roll into unincorporated areas of the County of San Diego — Tiny Homes on Wheels.",
                "pre_snippet": "10/01/2025 00:00:00",
                "extended_snippet": null,
                "images": null,
                "amp_version": false,
                "rating": null,
                "price": null,
                "highlighted": [
                  "unincorporated areas of the County of San Diego"
                ],
                "links": null,
                "faq": null,
                "extended_people_also_search": null,
                "about_this_result": null,
                "related_result": null,
                "timestamp": "2025-10-01 00:00:00 +00:00",
                "rectangle": null
              },
              {
                "type": "organic",
                "rank_group": 4,
                "rank_absolute": 7,
                "page": 1,
                "position": "left",
                "xpath": "/html[1]/body[1]/div[3]/div[1]/div[12]/div[1]/div[2]/div[2]/div[1]/div[1]/div[11]/div[1]/div[1]/div[1]",
                "domain": "www.youtube.com",
                "title": "San Diego's 1st Legal Tiny House Community! Insights & Tours",
                "url": "https://www.youtube.com/watch?v=C9NjfDJugkw",
                "cache_url": null,
                "related_search_url": null,
                "breadcrumb": "381.7K+ views  ·  6 years ago",
                "website_name": "YouTube · Tiny House Expedition",
                "is_image": false,
                "is_video": true,
                "is_featured_snippet": false,
                "is_malicious": false,
                "is_web_story": false,
                "description": null,
                "pre_snippet": null,
                "extended_snippet": null,
                "images": null,
                "amp_version": false,
                "rating": null,
                "price": null,
                "highlighted": null,
                "links": null,
                "faq": null,
                "extended_people_also_search": null,
                "about_this_result": null,
                "related_result": null,
                "timestamp": "2020-04-10 00:00:00 +00:00",
                "rectangle": null
              },
              {
                "type": "organic",
                "rank_group": 5,
                "rank_absolute": 8,
                "page": 1,
                "position": "left",
                "xpath": "/html[1]/body[1]/div[3]/div[1]/div[12]/div[1]/div[2]/div[2]/div[1]/div[1]/div[13]/div[1]/div[1]",
                "domain": "clevertinyhomes.com",
                "title": "The 7 Best Tiny Home Builders in San Diego (2025 Edition)",
                "url": "https://clevertinyhomes.com/blog/the-7-best-tiny-home-builders-in-san-diego-2025",
                "cache_url": null,
                "related_search_url": null,
                "breadcrumb": "https://clevertinyhomes.com › Blog",
                "website_name": "Clever Tiny Homes",
                "is_image": false,
                "is_video": false,
                "is_featured_snippet": false,
                "is_malicious": false,
                "is_web_story": false,
                "description": "Oct 27, 2025 — Planning a tiny home in San Diego? Here are seven reputable THOW builders serving the area, so you can compare options and move forward with ...",
                "pre_snippet": "10/27/2025 00:00:00",
                "extended_snippet": null,
                "images": null,
                "amp_version": false,
                "rating": null,
                "price": null,
                "highlighted": [
                  "seven reputable THOW builders serving the area"
                ],
                "links": null,
                "faq": null,
                "extended_people_also_search": null,
                "about_this_result": null,
                "related_result": null,
                "timestamp": "2025-10-27 00:00:00 +00:00",
                "rectangle": null
              },
              {
                "type": "short_videos",
                "rank_group": 1,
                "rank_absolute": 9,
                "page": 1,
                "position": "left",
                "xpath": "/html[1]/body[1]/div[3]/div[1]/div[12]/div[1]/div[2]/div[2]/div[1]/div[1]/div[15]/div[1]",
                "title": "Short videos",
                "items": [
                  {
                    "type": "short_videos_element",
                    "title": "Inside San Diego's first legal tiny house village #TinyHouse ...",
                    "url": "https://www.facebook.com/TinyHouseExpedition/videos/inside-san-diegos-first-legal-tiny-house-village/1934186710840674/",
                    "domain": "www.facebook.com",
                    "source": "Tiny House Expedition"
                  },
                  {
                    "type": "short_videos_element",
                    "title": "Would you live in this ~$30K tiny home we found at TinyFest ...",
                    "url": "https://www.facebook.com/dreambiglivetiny/videos/would-you-live-in-this-30k-tiny-home-we-found-at-tinyfest-san-diego-built-by-cre/1715098876274544/",
                    "domain": "www.facebook.com",
                    "source": "Dream Big Live Tiny Co."
                  },
                  {
                    "type": "short_videos_element",
                    "title": "A home in San Diego, but at a price that's unheard of ...",
                    "url": "https://www.instagram.com/reel/DVEa2fekk9E/",
                    "domain": "www.instagram.com",
                    "source": "Tiny and Unique Home Tours | Jenna"
                  },
                  {
                    "type": "short_videos_element",
                    "title": "Tiny Homes on Wheels — A Game Changer for San Diego ...",
                    "url": "https://www.instagram.com/reel/DRNOQMSD2Dd/",
                    "domain": "www.instagram.com",
                    "source": "McT Real Estate Group - San Diego Realtors"
                  },
                  {
                    "type": "short_videos_element",
                    "title": "What do you think of this 26' tiny house for $54999? Would ...",
                    "url": "https://www.facebook.com/dreambiglivetiny/videos/what-do-you-think-of-this-26-tiny-house-for-54999-would-you-live-in-itthis-is-th/780670518317360/",
                    "domain": "www.facebook.com",
                    "source": "Dream Big Live Tiny Co."
                  },
                  {
                    "type": "short_videos_element",
                    "title": "NBC 7 San Diego on Instagram: \"A new housing option is ...",
                    "url": "https://www.instagram.com/reel/DPctp9gAT3g/",
                    "domain": "www.instagram.com",
                    "source": "NBC 7 San Diego"
                  },
                  {
                    "type": "short_videos_element",
                    "title": "What do you think of this 26' tiny house for $54999? Would ...",
                    "url": "https://www.facebook.com/dreambiglivetiny/videos/what-do-you-think-of-this-26-tiny-house-for-54999-would-you-live-in-itthis-is-th/960721116492831/",
                    "domain": "www.facebook.com",
                    "source": "Dream Big Live Tiny Co."
                  },
                  {
                    "type": "short_videos_element",
                    "title": "What do you think of this 26' tiny house for $54,999? Would ...",
                    "url": "https://www.facebook.com/dreambiglivetiny/videos/what-do-you-think-of-this-26-tiny-house-for-54999-would-you-live-in-itthis-is-th/1705198613970285/",
                    "domain": "www.facebook.com",
                    "source": "Dream Big Live Tiny Co."
                  },
                  {
                    "type": "short_videos_element",
                    "title": "What do you think of this 26' tiny house for $54,999? Would ...",
                    "url": "https://www.facebook.com/dreambiglivetiny/videos/220-sqft-single-level-tiny-house-/1653231888984808/",
                    "domain": "www.facebook.com",
                    "source": "Dream Big Live Tiny Co."
                  },
                  {
                    "type": "short_videos_element",
                    "title": "Tiny Home Tours on Instagram: \"She always loved tiny houses ...",
                    "url": "https://www.instagram.com/reel/DQUsaSSETVf/",
                    "domain": "www.instagram.com",
                    "source": "Tiny Home Tours"
                  }
                ],
                "rectangle": null
              },
              {
                "type": "organic",
                "rank_group": 6,
                "rank_absolute": 10,
                "page": 1,
                "position": "left",
                "xpath": "/html[1]/body[1]/div[3]/div[1]/div[12]/div[1]/div[2]/div[2]/div[1]/div[1]/div[17]/div[1]/div[1]",
                "domain": "www.facebook.com",
                "title": "Tiny House San Diego",
                "url": "https://www.facebook.com/groups/tinyhousesandiego/",
                "cache_url": null,
                "related_search_url": null,
                "breadcrumb": "6.8K+ followers",
                "website_name": "Facebook · Tiny House San Diego",
                "is_image": false,
                "is_video": false,
                "is_featured_snippet": false,
                "is_malicious": false,
                "is_web_story": false,
                "description": "The Tiny House San Diego Facebook group is a place for tiny home information and discussions for the San Diego region. ranges $1200 - $1500/mo. Tiny House ...",
                "pre_snippet": null,
                "extended_snippet": null,
                "images": null,
                "amp_version": false,
                "rating": null,
                "price": null,
                "highlighted": [
                  "ranges $1200 - $1500/mo"
                ],
                "links": null,
                "faq": null,
                "extended_people_also_search": null,
                "about_this_result": null,
                "related_result": null,
                "timestamp": null,
                "rectangle": null
              },
              {
                "type": "organic",
                "rank_group": 7,
                "rank_absolute": 11,
                "page": 1,
                "position": "left",
                "xpath": "/html[1]/body[1]/div[3]/div[1]/div[12]/div[1]/div[2]/div[2]/div[1]/div[1]/div[19]/div[1]/div[1]",
                "domain": "www.rentthebackyard.com",
                "title": "Best Tiny Homes for Sale in San Diego, California",
                "url": "https://www.rentthebackyard.com/location/tiny-homes-san-diego-california",
                "cache_url": null,
                "related_search_url": null,
                "breadcrumb": "https://www.rentthebackyard.com › location › tiny-hom...",
                "website_name": "rentthebackyard.com",
                "is_image": false,
                "is_video": false,
                "is_featured_snippet": false,
                "is_malicious": false,
                "is_web_story": false,
                "description": "Tiny homes under $200k in San Diego. Aspen. $79,900. Aspen. The Aspen is a 312 sq ft, 1-bathroom prefab tiny home from Great Lakes Tiny Homes. Learn more. Scale ... Read more",
                "pre_snippet": null,
                "extended_snippet": null,
                "images": null,
                "amp_version": false,
                "rating": null,
                "price": null,
                "highlighted": [
                  "Tiny homes under $200k in San Diego"
                ],
                "links": null,
                "faq": null,
                "extended_people_also_search": null,
                "about_this_result": null,
                "related_result": null,
                "timestamp": null,
                "rectangle": null
              },
              {
                "type": "related_searches",
                "rank_group": 1,
                "rank_absolute": 12,
                "page": 1,
                "position": "left",
                "xpath": "/html[1]/body[1]/div[3]/div[1]/div[12]/div[1]/div[3]/div[1]/div[3]/div[1]/div[1]/div[1]/div[1]/div[2]",
                "items": [
                  "Tiny house san diego for sale",
                  "Tiny house san diego for rent",
                  "Tiny home Community San Diego prices",
                  "Tiny house san diego cost",
                  "Tiny house san diego price",
                  "Used tiny house san diego",
                  "Clever Tiny homes San Diego",
                  "Tiny homes on wheels san diego"
                ],
                "rectangle": null
              },
              {
                "type": "organic",
                "rank_group": 8,
                "rank_absolute": 13,
                "page": 2,
                "position": "left",
                "xpath": "/html[1]/body[1]/div[3]/div[1]/div[12]/div[1]/div[2]/div[2]/div[1]/div[1]/div[1]/div[1]/div[1]",
                "domain": "www.reddit.com",
                "title": "I want a tiny house - here in San Diego CA - any tips?",
                "url": "https://www.reddit.com/r/TinyHouses/comments/1eqz449/i_want_a_tiny_house_here_in_san_diego_ca_any_tips/",
                "cache_url": null,
                "related_search_url": null,
                "breadcrumb": "20+ comments  ·  1 year ago",
                "website_name": "Reddit · r/TinyHouses",
                "is_image": false,
                "is_video": false,
                "is_featured_snippet": false,
                "is_malicious": false,
                "is_web_story": false,
                "description": "It's called the tiny house block. $900 to rent a spot if you bring your home, $1400-$1600 to rent a tiny there I believe. it's an hour away ...",
                "pre_snippet": null,
                "extended_snippet": null,
                "images": null,
                "amp_version": false,
                "rating": null,
                "price": null,
                "highlighted": [
                  "900 to rent a spot if you bring your home"
                ],
                "links": null,
                "faq": null,
                "extended_people_also_search": null,
                "about_this_result": null,
                "related_result": null,
                "timestamp": null,
                "rectangle": null
              },
              {
                "type": "organic",
                "rank_group": 9,
                "rank_absolute": 14,
                "page": 2,
                "position": "left",
                "xpath": "/html[1]/body[1]/div[3]/div[1]/div[12]/div[1]/div[2]/div[2]/div[1]/div[1]/div[2]/div[1]/div[1]",
                "domain": "www.airbnb.com",
                "title": "Tiny house vacation rentals in San Diego",
                "url": "https://www.airbnb.com/san-diego-ca/stays/tiny-houses",
                "cache_url": null,
                "related_search_url": null,
                "breadcrumb": "https://www.airbnb.com › ... › San Diego",
                "website_name": "Airbnb",
                "is_image": false,
                "is_video": false,
                "is_featured_snippet": false,
                "is_malicious": false,
                "is_web_story": false,
                "description": "Top-rated tiny house rentals in San Diego. Guests agree: these tiny house rentals are highly rated for location, cleanliness, and more. Read more",
                "pre_snippet": null,
                "extended_snippet": null,
                "images": null,
                "amp_version": false,
                "rating": {
                  "rating_type": "Max5",
                  "value": 4.9,
                  "votes_count": 1091,
                  "rating_max": 5
                },
                "price": null,
                "highlighted": [
                  "Top-rated tiny house rentals in San Diego"
                ],
                "links": null,
                "faq": null,
                "extended_people_also_search": null,
                "about_this_result": null,
                "related_result": null,
                "timestamp": null,
                "rectangle": null
              },
              {
                "type": "organic",
                "rank_group": 10,
                "rank_absolute": 15,
                "page": 2,
                "position": "left",
                "xpath": "/html[1]/body[1]/div[3]/div[1]/div[12]/div[1]/div[2]/div[2]/div[1]/div[1]/div[3]/div[1]/div[1]",
                "domain": "www.instagram.com",
                "title": "Zen Tiny Homes (@zentinyhomes) · Vista, CA",
                "url": "https://www.instagram.com/zentinyhomes/?hl=en",
                "cache_url": null,
                "related_search_url": null,
                "breadcrumb": "43.7K+ followers",
                "website_name": "Instagram · zentinyhomes",
                "is_image": false,
                "is_video": false,
                "is_featured_snippet": false,
                "is_malicious": false,
                "is_web_story": false,
                "description": "San Diego's favorite tiny home builder. As seen on HGTV/CBS/KPBS. We plan, design & build custom small homes. Reserve your custom build with us today. Read more",
                "pre_snippet": null,
                "extended_snippet": null,
                "images": null,
                "amp_version": false,
                "rating": null,
                "price": null,
                "highlighted": [
                  "San Diego's favorite tiny home builder"
                ],
                "links": null,
                "faq": null,
                "extended_people_also_search": null,
                "about_this_result": null,
                "related_result": null,
                "timestamp": null,
                "rectangle": null
              },
              {
                "type": "organic",
                "rank_group": 11,
                "rank_absolute": 16,
                "page": 2,
                "position": "left",
                "xpath": "/html[1]/body[1]/div[3]/div[1]/div[12]/div[1]/div[2]/div[2]/div[1]/div[1]/div[4]/div[1]/div[1]",
                "domain": "www.craigslist.org",
                "title": "san diego for sale \"tiny house\"",
                "url": "https://www.craigslist.org/search/area/sandiego?cat=sss&query=tiny%20house",
                "cache_url": null,
                "related_search_url": null,
                "breadcrumb": "https://www.craigslist.org › for sale",
                "website_name": "craigslist",
                "is_image": false,
                "is_video": false,
                "is_featured_snippet": false,
                "is_malicious": false,
                "is_web_story": false,
                "description": "craigslist. For Sale \"tiny house\" in San Diego. see also. TINY HOUSE ON WHEELS NO PERMIT NEEDED READY TO LIVE IN. $75,450. south san diego county.",
                "pre_snippet": null,
                "extended_snippet": null,
                "images": null,
                "amp_version": false,
                "rating": null,
                "price": null,
                "highlighted": [
                  "For Sale \"tiny house\" in San Diego"
                ],
                "links": null,
                "faq": null,
                "extended_people_also_search": null,
                "about_this_result": null,
                "related_result": null,
                "timestamp": null,
                "rectangle": null
              },
              {
                "type": "organic",
                "rank_group": 12,
                "rank_absolute": 17,
                "page": 2,
                "position": "left",
                "xpath": "/html[1]/body[1]/div[3]/div[1]/div[12]/div[1]/div[2]/div[2]/div[1]/div[1]/div[5]/div[1]/div[1]",
                "domain": "tinyhomecentral.org",
                "title": "Tiny Homes in REAL LIFE - How to make tiny house living ...",
                "url": "https://tinyhomecentral.org/",
                "cache_url": null,
                "related_search_url": null,
                "breadcrumb": "https://tinyhomecentral.org",
                "website_name": "tinyhomecentral.org",
                "is_image": false,
                "is_video": false,
                "is_featured_snippet": false,
                "is_malicious": false,
                "is_web_story": false,
                "description": "We permitted the first Movable Tiny House in the San Diego region. Urban Corps of San Diego County students built this first tiny house, as shown above. Read more",
                "pre_snippet": null,
                "extended_snippet": null,
                "images": null,
                "amp_version": false,
                "rating": null,
                "price": null,
                "highlighted": [
                  "Urban Corps of San Diego County students built this first tiny house"
                ],
                "links": null,
                "faq": null,
                "extended_people_also_search": null,
                "about_this_result": null,
                "related_result": null,
                "timestamp": null,
                "rectangle": null
              },
              {
                "type": "organic",
                "rank_group": 13,
                "rank_absolute": 18,
                "page": 2,
                "position": "left",
                "xpath": "/html[1]/body[1]/div[3]/div[1]/div[12]/div[1]/div[2]/div[2]/div[1]/div[1]/div[6]/div[1]/div[1]",
                "domain": "www.10news.com",
                "title": "Tiny house village invites people to live with less",
                "url": "https://www.10news.com/lifestyle/exploring-san-diego/san-diegos-first-tiny-house-village-invites-people-to-live-with-less",
                "cache_url": null,
                "related_search_url": null,
                "breadcrumb": "https://www.10news.com › exploring-san-diego › san-d...",
                "website_name": "10News.com",
                "is_image": false,
                "is_video": false,
                "is_featured_snippet": false,
                "is_malicious": false,
                "is_web_story": false,
                "description": "Jun 12, 2019 — It's called Tiny House Block and is currently made up of 10 tiny homes nestled in Mt. Laguna. \"The vision of Tiny House Block is to create a ... Read more",
                "pre_snippet": "06/12/2019 00:00:00",
                "extended_snippet": null,
                "images": null,
                "amp_version": false,
                "rating": null,
                "price": null,
                "highlighted": [
                  "currently made up of 10 tiny homes nestled in Mt. Laguna"
                ],
                "links": null,
                "faq": null,
                "extended_people_also_search": null,
                "about_this_result": null,
                "related_result": null,
                "timestamp": "2019-06-12 00:00:00 +00:00",
                "rectangle": null
              },
              {
                "type": "organic",
                "rank_group": 14,
                "rank_absolute": 19,
                "page": 2,
                "position": "left",
                "xpath": "/html[1]/body[1]/div[3]/div[1]/div[12]/div[1]/div[2]/div[2]/div[1]/div[1]/div[7]/div[1]/div[1]",
                "domain": "movabletinyhomes.com",
                "title": "REBUILDING GREEN - Tiny Homes, Tiny House Plans ...",
                "url": "https://movabletinyhomes.com/",
                "cache_url": null,
                "related_search_url": null,
                "breadcrumb": "https://movabletinyhomes.com",
                "website_name": "rebuilding green",
                "is_image": false,
                "is_video": false,
                "is_featured_snippet": false,
                "is_malicious": false,
                "is_web_story": false,
                "description": "Tiny homes are an affordable housing solution, period! Whether manufactured home or custom green-built as a primary or ADU 2nd unit, we have many options!",
                "pre_snippet": null,
                "extended_snippet": null,
                "images": null,
                "amp_version": false,
                "rating": null,
                "price": null,
                "highlighted": [
                  "Tiny homes are an affordable housing solution"
                ],
                "links": null,
                "faq": null,
                "extended_people_also_search": null,
                "about_this_result": null,
                "related_result": null,
                "timestamp": null,
                "rectangle": null
              },
              {
                "type": "images",
                "rank_group": 1,
                "rank_absolute": 20,
                "page": 2,
                "position": "left",
                "xpath": "/html[1]/body[1]/div[3]/div[1]/div[12]/div[1]/div[2]/div[2]/div[1]/div[1]/div[8]/div[1]",
                "title": "Images",
                "url": "https://www.google.com/search?sa=N&hl=en&gl=US&sca_esv=a687d299647ce93d&q=tiny+house+san+diego&udm=2&source=univ&fir=7EnrUlV2vIjv5M%252CikPd3g25k57IuM%252C_%253BQFiG88lR5JbqbM%252CMk4O2C4aCcgaRM%252C_%253BSaXVLLIdGsI1VM%252C72vFEkCoh9LsAM%252C_%253BDSr1CAyqVzmisM%252CmCSumxEQEIE2LM%252C_%253B_AXecW_IfbkxBM%252CUgVsgpXt55NN-M%252C_%253BS0A2yyo4uULv8M%252CEudIj851yP9d4M%252C_%253BW4pWE2GlZBgJJM%252CUJKLBJ5qqbDtTM%252C_%253BTjrUNd9REclVlM%252CqRzuP6zJGk_wpM%252C_%253BzvbseKgWQe_KdM%252CpDOXIgbBVuFiMM%252C_&usg=AI4_-kTftxuLcSo76ZSz8J7jhpWyro6Qbw&ved=2ahUKEwi8sfyqztyVAxU_oCsGHVtrKSI4ChDsCXoECDQQBQ",
                "items": [
                  {
                    "type": "images_element",
                    "alt": "San Diego's 1st Legal Tiny House Community! Insights & Tours",
                    "url": "https://www.youtube.com/watch?v=C9NjfDJugkw",
                    "image_url": "https://api.dataforseo.com/cdn/i/07181909-2024-0139-0000-1b3d7a100403:0"
                  },
                  {
                    "type": "images_element",
                    "alt": "Tiny Homes In San Diego Face Big Hurdles | KPBS Public Media",
                    "url": "https://www.kpbs.org/news/midday-edition/2017/09/21/big-hurdles-tiny-homes-san-diego",
                    "image_url": "https://api.dataforseo.com/cdn/i/07181909-2024-0139-0000-1b3d7a100403:1"
                  },
                  {
                    "type": "images_element",
                    "alt": "San Diego's #1 Tiny Home Builder, Zen Tiny Homes",
                    "url": "https://www.zentinyhomes.com/",
                    "image_url": "https://api.dataforseo.com/cdn/i/07181909-2024-0139-0000-1b3d7a100403:2"
                  },
                  {
                    "type": "images_element",
                    "alt": "Tiny House for Sale - Tiny House In San Diego",
                    "url": "https://www.tinyhomebuilders.com/tiny-house-marketplace/tiny-house-in-san-diego",
                    "image_url": "https://encrypted-tbn0.gstatic.com/images?q=tbn:ANd9GcQIzmoLrbAfEdZP1PDZUo0KxYk7Q19ligFNkDdIoiK_erEHLijjtMgMoks&s"
                  },
                  {
                    "type": "images_element",
                    "alt": "'Tiny homes' in high demand; Here's how to get one in San Diego",
                    "url": "https://www.youtube.com/watch?v=Blk6qSUHR9g",
                    "image_url": "https://encrypted-tbn0.gstatic.com/images?q=tbn:ANd9GcTMbqhvLWtcuUAg2dcrts7dzGyScoHCF6jZZz5DPKSz&s"
                  },
                  {
                    "type": "images_element",
                    "alt": "The 7 Best Tiny Home Builders in San Diego (2025 Edition ...",
                    "url": "https://clevertinyhomes.com/blog/the-7-best-tiny-home-builders-in-san-diego-2025",
                    "image_url": "https://encrypted-tbn0.gstatic.com/images?q=tbn:ANd9GcRZsps_3sGitt9_PaCMPc6P9HhmGwznE0-Za_FI9PBlrEWW5_DjF9iuszs&s"
                  },
                  {
                    "type": "images_element",
                    "alt": "Featured Tiny Home Community: Tiny House Block – Choose Tiny",
                    "url": "https://choosetiny.com/featured-tiny-home-community-tiny-house-block/",
                    "image_url": "https://encrypted-tbn0.gstatic.com/images?q=tbn:ANd9GcTbzYszP4PIpBI2r3DmACZI0QmLS1q-8i4uXwvW8hBB_syyjKHItGr3R8g&s"
                  },
                  {
                    "type": "images_element",
                    "alt": "How to get 'tiny homes' in San Diego",
                    "url": "https://www.10news.com/news/making-it-in-san-diego/tiny-homes-in-high-demand-heres-how-to-get-one-in-san-diego",
                    "image_url": "https://encrypted-tbn0.gstatic.com/images?q=tbn:ANd9GcSPPFxDW5wZLRIjJQtL2ykDQknVADV9TR4L7Sf79qKm8k-8BioaPX8uXME&s"
                  },
                  {
                    "type": "images_element",
                    "alt": "Tiny House San Diego | Facebook",
                    "url": "https://www.facebook.com/groups/tinyhousesandiego/",
                    "image_url": "https://encrypted-tbn0.gstatic.com/images?q=tbn:ANd9GcQKYelt_UN3JlycP8UPKtNBfqrKZL4h-Io7JJaYASYkwIxshz4AYElSPoI&s"
                  }
                ],
                "related_image_searches": null,
                "rectangle": null
              },
              {
                "type": "organic",
                "rank_group": 15,
                "rank_absolute": 21,
                "page": 2,
                "position": "left",
                "xpath": "/html[1]/body[1]/div[3]/div[1]/div[12]/div[1]/div[2]/div[2]/div[1]/div[1]/div[9]/div[1]/div[1]",
                "domain": "www.nbcsandiego.com",
                "title": "Tiny homes roll into San Diego in hopes of combating ...",
                "url": "https://www.nbcsandiego.com/news/local/tiny-homes-san-diego-housing-crisis/3910642/",
                "cache_url": null,
                "related_search_url": null,
                "breadcrumb": "https://www.nbcsandiego.com › news › local › tiny-ho...",
                "website_name": "NBC 7 San Diego",
                "is_image": false,
                "is_video": false,
                "is_featured_snippet": false,
                "is_malicious": false,
                "is_web_story": false,
                "description": "Oct 3, 2025 — County planners will now allow tiny homes on wheels to qualify as standalone homes in unincorporated areas of San Diego.",
                "pre_snippet": "10/03/2025 00:00:00",
                "extended_snippet": null,
                "images": null,
                "amp_version": false,
                "rating": null,
                "price": null,
                "highlighted": [
                  "tiny",
                  "San Diego"
                ],
                "links": null,
                "faq": null,
                "extended_people_also_search": null,
                "about_this_result": null,
                "related_result": null,
                "timestamp": "2025-10-03 00:00:00 +00:00",
                "rectangle": null
              },
              {
                "type": "organic",
                "rank_group": 16,
                "rank_absolute": 22,
                "page": 2,
                "position": "left",
                "xpath": "/html[1]/body[1]/div[3]/div[1]/div[12]/div[1]/div[2]/div[2]/div[1]/div[1]/div[10]/div[1]/div[1]",
                "domain": "www.landsearch.com",
                "title": "San Diego County, CA Tiny Homes With Land for Sale",
                "url": "https://www.landsearch.com/tiny-home/san-diego-county-ca",
                "cache_url": null,
                "related_search_url": null,
                "breadcrumb": "https://www.landsearch.com › ... › Southern California",
                "website_name": "LandSearch",
                "is_image": false,
                "is_video": false,
                "is_featured_snippet": false,
                "is_malicious": false,
                "is_web_story": false,
                "description": "There are currently 2 tiny homes with land for sale in San Diego County, with an average listing price of $525,400. The average cost to buy is $72,569 per acre. Read more",
                "pre_snippet": null,
                "extended_snippet": null,
                "images": null,
                "amp_version": false,
                "rating": null,
                "price": null,
                "highlighted": [
                  "currently 2 tiny homes with land for sale in San Diego County"
                ],
                "links": null,
                "faq": null,
                "extended_people_also_search": null,
                "about_this_result": null,
                "related_result": null,
                "timestamp": null,
                "rectangle": null
              },
              {
                "type": "related_searches",
                "rank_group": 2,
                "rank_absolute": 23,
                "page": 2,
                "position": "left",
                "xpath": "/html[1]/body[1]/div[3]/div[1]/div[12]/div[1]/div[3]/div[1]/div[3]/div[1]/div[1]/div[1]/div[1]/div[2]",
                "items": [
                  "Tiny house san diego for sale",
                  "Tiny house san diego for rent",
                  "Tiny home Community San Diego prices",
                  "Tiny house san diego cost",
                  "Tiny house san diego price",
                  "Used tiny house san diego",
                  "Clever Tiny homes San Diego",
                  "Tiny homes on wheels san diego"
                ],
                "rectangle": null
              },
              {
                "type": "organic",
                "rank_group": 17,
                "rank_absolute": 24,
                "page": 3,
                "position": "left",
                "xpath": "/html[1]/body[1]/div[3]/div[1]/div[12]/div[1]/div[2]/div[2]/div[1]/div[1]/div[1]/div[1]/div[1]/div[1]",
                "domain": "www.nbcsandiego.com",
                "title": "60 tiny homes coming to Lemon Grove – NBC 7 San Diego",
                "url": "https://www.nbcsandiego.com/video/videos/60-tiny-homes-coming-to-lemon-grove/3998849/",
                "cache_url": null,
                "related_search_url": null,
                "breadcrumb": "https://www.nbcsandiego.com · Mar 22, 2026",
                "website_name": "NBC 7 San Diego",
                "is_image": false,
                "is_video": true,
                "is_featured_snippet": false,
                "is_malicious": false,
                "is_web_story": false,
                "description": "60 tiny homes coming to Lemon Grove. A controversial tiny home project in Lemon Grove is moving forward. The proposed development is slated to ...",
                "pre_snippet": null,
                "extended_snippet": null,
                "images": null,
                "amp_version": false,
                "rating": null,
                "price": null,
                "highlighted": [
                  "60 tiny homes coming to Lemon Grove"
                ],
                "links": null,
                "faq": null,
                "extended_people_also_search": null,
                "about_this_result": null,
                "related_result": null,
                "timestamp": "2026-03-22 00:00:00 +00:00",
                "rectangle": null
              },
              {
                "type": "organic",
                "rank_group": 18,
                "rank_absolute": 25,
                "page": 3,
                "position": "left",
                "xpath": "/html[1]/body[1]/div[3]/div[1]/div[12]/div[1]/div[2]/div[2]/div[1]/div[1]/div[2]/div[1]/div[1]",
                "domain": "tinyhouseblock.com",
                "title": "Tiny House Block | Live the Tiny Life on Mount Laguna",
                "url": "https://tinyhouseblock.com/",
                "cache_url": null,
                "related_search_url": null,
                "breadcrumb": "https://tinyhouseblock.com",
                "website_name": "Tiny House Block",
                "is_image": false,
                "is_video": false,
                "is_featured_snippet": false,
                "is_malicious": false,
                "is_web_story": false,
                "description": "If you haven't bought a Tiny yet, you can still enjoy to the the minimal life by leasing ours! Wake up everyday to fresh air and the relaxation that comes from. Read more",
                "pre_snippet": null,
                "extended_snippet": null,
                "images": null,
                "amp_version": false,
                "rating": null,
                "price": null,
                "highlighted": [
                  "our"
                ],
                "links": null,
                "faq": null,
                "extended_people_also_search": null,
                "about_this_result": null,
                "related_result": null,
                "timestamp": null,
                "rectangle": null
              },
              {
                "type": "organic",
                "rank_group": 19,
                "rank_absolute": 26,
                "page": 3,
                "position": "left",
                "xpath": "/html[1]/body[1]/div[3]/div[1]/div[12]/div[1]/div[2]/div[2]/div[1]/div[1]/div[3]/div[1]/div[1]/div[1]",
                "domain": "www.instagram.com",
                "title": "NBC 7 San Diego on Instagram: \"A new housing option is ...",
                "url": "https://www.instagram.com/reel/DPctp9gAT3g/",
                "cache_url": null,
                "related_search_url": null,
                "breadcrumb": "850+ likes  ·  9 months ago",
                "website_name": "Instagram · nbcsandiego",
                "is_image": false,
                "is_video": true,
                "is_featured_snippet": false,
                "is_malicious": false,
                "is_web_story": false,
                "description": "County planners will now allow tiny homes on wheels to qualify as standalone homes in unincorporated areas of San Diego.⁠ ⁠ NBC 7's @shandeltv ...",
                "pre_snippet": null,
                "extended_snippet": null,
                "images": null,
                "amp_version": false,
                "rating": null,
                "price": null,
                "highlighted": [
                  "County planners will now allow tiny homes on wheels to qualify as standalone homes"
                ],
                "links": null,
                "faq": null,
                "extended_people_also_search": null,
                "about_this_result": null,
                "related_result": null,
                "timestamp": "2025-10-18 16:09:22 +00:00",
                "rectangle": null
              },
              {
                "type": "organic",
                "rank_group": 20,
                "rank_absolute": 27,
                "page": 3,
                "position": "left",
                "xpath": "/html[1]/body[1]/div[3]/div[1]/div[12]/div[1]/div[2]/div[2]/div[1]/div[1]/div[4]/div[1]/div[1]",
                "domain": "greatlakestinyhome.com",
                "title": "Tiny Houses & Homes For Sale In San Diego",
                "url": "https://greatlakestinyhome.com/locations/california/san-diego/",
                "cache_url": null,
                "related_search_url": null,
                "breadcrumb": "https://greatlakestinyhome.com › California",
                "website_name": "Great Lakes Tiny Home",
                "is_image": false,
                "is_video": false,
                "is_featured_snippet": false,
                "is_malicious": false,
                "is_web_story": false,
                "description": "Discover our RVIA-certified, modern, custom-built tiny house models for San Diego Built with the best materials and 100+ years of combined craftsmanship!",
                "pre_snippet": null,
                "extended_snippet": null,
                "images": null,
                "amp_version": false,
                "rating": null,
                "price": null,
                "highlighted": [
                  "RVIA-certified, modern, custom-built tiny house models for San Diego"
                ],
                "links": null,
                "faq": null,
                "extended_people_also_search": null,
                "about_this_result": null,
                "related_result": null,
                "timestamp": null,
                "rectangle": null
              },
              {
                "type": "organic",
                "rank_group": 21,
                "rank_absolute": 28,
                "page": 3,
                "position": "left",
                "xpath": "/html[1]/body[1]/div[3]/div[1]/div[12]/div[1]/div[2]/div[2]/div[1]/div[1]/div[5]/div[1]/div[1]/div[1]",
                "domain": "www.facebook.com",
                "title": "San Diego's 1st Legal Tiny House Community! 🏘️ Tiny ...",
                "url": "https://www.facebook.com/TinyHouseExpedition/videos/san-diegos-1st-legal-tiny-house-community-insights-tours/4408254202832314/",
                "cache_url": null,
                "related_search_url": null,
                "breadcrumb": "550+ reactions  ·  7 months ago",
                "website_name": "Facebook · Tiny House Expedition",
                "is_image": false,
                "is_video": true,
                "is_featured_snippet": false,
                "is_malicious": false,
                "is_web_story": false,
                "description": "San Diego's 1st Legal Tiny House Community ! 🏘️   Tiny House Block · Bonnie Jenkins and 558 others · 󰍸 559 · 󰍹 17 · 󰤧 30. Profile photo of Cynthia.",
                "pre_snippet": null,
                "extended_snippet": null,
                "images": null,
                "amp_version": false,
                "rating": null,
                "price": null,
                "highlighted": [
                  "San Diego's 1st Legal Tiny House Community"
                ],
                "links": null,
                "faq": null,
                "extended_people_also_search": null,
                "about_this_result": null,
                "related_result": null,
                "timestamp": "2025-12-18 16:09:22 +00:00",
                "rectangle": null
              },
              {
                "type": "organic",
                "rank_group": 22,
                "rank_absolute": 29,
                "page": 3,
                "position": "left",
                "xpath": "/html[1]/body[1]/div[3]/div[1]/div[12]/div[1]/div[2]/div[2]/div[1]/div[1]/div[6]/div[1]/div[1]",
                "domain": "www.airbnb.com",
                "title": "Tiny house vacation rentals in San Diego County",
                "url": "https://www.airbnb.com/san-diego-county-ca/stays/tiny-houses",
                "cache_url": null,
                "related_search_url": null,
                "breadcrumb": "https://www.airbnb.com › ... › San Diego County",
                "website_name": "Airbnb",
                "is_image": false,
                "is_video": false,
                "is_featured_snippet": false,
                "is_malicious": false,
                "is_web_story": false,
                "description": "Top-rated tiny house rentals in San Diego County. Guests agree: these tiny house rentals are highly rated for location, cleanliness, and more. Read more",
                "pre_snippet": null,
                "extended_snippet": null,
                "images": null,
                "amp_version": false,
                "rating": {
                  "rating_type": "Max5",
                  "value": 4.9,
                  "votes_count": 1090,
                  "rating_max": 5
                },
                "price": null,
                "highlighted": [
                  "Top-rated tiny house rentals in San Diego County"
                ],
                "links": null,
                "faq": null,
                "extended_people_also_search": null,
                "about_this_result": null,
                "related_result": null,
                "timestamp": null,
                "rectangle": null
              },
              {
                "type": "organic",
                "rank_group": 23,
                "rank_absolute": 30,
                "page": 3,
                "position": "left",
                "xpath": "/html[1]/body[1]/div[3]/div[1]/div[12]/div[1]/div[2]/div[2]/div[1]/div[1]/div[7]/div[1]/div[1]",
                "domain": "tinyhouselistings.com",
                "title": "san diego tiny homes by melissa",
                "url": "https://tinyhouselistings.com/dreamlists/san-diego-tiny-homes",
                "cache_url": null,
                "related_search_url": null,
                "breadcrumb": "https://tinyhouselistings.com › dreamlists › san-diego-ti...",
                "website_name": "Tiny House Listings",
                "is_image": false,
                "is_video": false,
                "is_featured_snippet": false,
                "is_malicious": false,
                "is_web_story": false,
                "description": "A collection of tiny houses by melissa.",
                "pre_snippet": null,
                "extended_snippet": null,
                "images": null,
                "amp_version": false,
                "rating": null,
                "price": null,
                "highlighted": [
                  "tiny"
                ],
                "links": null,
                "faq": null,
                "extended_people_also_search": null,
                "about_this_result": null,
                "related_result": null,
                "timestamp": null,
                "rectangle": null
              },
              {
                "type": "organic",
                "rank_group": 24,
                "rank_absolute": 31,
                "page": 3,
                "position": "left",
                "xpath": "/html[1]/body[1]/div[3]/div[1]/div[12]/div[1]/div[2]/div[2]/div[1]/div[1]/div[8]/div[1]/div[1]",
                "domain": "www.yelp.com",
                "title": "TOP 10 BEST Tiny House Builders in San Diego, CA",
                "url": "https://www.yelp.com/search?find_desc=Tiny+House+Builders&find_loc=San+Diego%2C+CA",
                "cache_url": null,
                "related_search_url": null,
                "breadcrumb": "https://www.yelp.com › Home Services",
                "website_name": "Yelp",
                "is_image": false,
                "is_video": false,
                "is_featured_snippet": false,
                "is_malicious": false,
                "is_web_story": false,
                "description": "Top 10 Best Tiny House Builders Near San Diego, California · Two Element Builders · Elements Design & Build · Eco Home Builders · Better Place Design & Build. Read more",
                "pre_snippet": null,
                "extended_snippet": null,
                "images": null,
                "amp_version": false,
                "rating": {
                  "rating_type": "Max5",
                  "value": 4.5,
                  "votes_count": 14053,
                  "rating_max": 5
                },
                "price": null,
                "highlighted": [
                  "Two Element Builders"
                ],
                "links": null,
                "faq": null,
                "extended_people_also_search": null,
                "about_this_result": null,
                "related_result": null,
                "timestamp": null,
                "rectangle": null
              },
              {
                "type": "organic",
                "rank_group": 25,
                "rank_absolute": 32,
                "page": 3,
                "position": "left",
                "xpath": "/html[1]/body[1]/div[3]/div[1]/div[12]/div[1]/div[2]/div[2]/div[1]/div[1]/div[9]/div[1]/div[1]",
                "domain": "www.houzeo.com",
                "title": "108+ Tiny Homes for Sale in San Diego, California",
                "url": "https://www.houzeo.com/homes-for-sale/california/san-diego/tiny-homes-for-sale",
                "cache_url": null,
                "related_search_url": null,
                "breadcrumb": "https://www.houzeo.com › ... › California › San Diego",
                "website_name": "Houzeo",
                "is_image": false,
                "is_video": false,
                "is_featured_snippet": false,
                "is_malicious": false,
                "is_web_story": false,
                "description": "Discover 108 Tiny homes for sale in San Diego, California. Connect with agents, schedule tours, and submit offers easily on Houzeo, America's best home ...",
                "pre_snippet": null,
                "extended_snippet": null,
                "images": null,
                "amp_version": false,
                "rating": null,
                "price": null,
                "highlighted": [
                  "108 Tiny homes for sale in San Diego, California"
                ],
                "links": null,
                "faq": null,
                "extended_people_also_search": null,
                "about_this_result": null,
                "related_result": null,
                "timestamp": null,
                "rectangle": null
              },
              {
                "type": "organic",
                "rank_group": 26,
                "rank_absolute": 33,
                "page": 3,
                "position": "left",
                "xpath": "/html[1]/body[1]/div[3]/div[1]/div[12]/div[1]/div[2]/div[2]/div[1]/div[1]/div[10]/div[1]/div[1]",
                "domain": "tinyhousecottages.com",
                "title": "Contact Us Today for Custom Units",
                "url": "https://tinyhousecottages.com/contact-us/",
                "cache_url": null,
                "related_search_url": null,
                "breadcrumb": "https://tinyhousecottages.com › contact-us",
                "website_name": "Tiny House Cottages",
                "is_image": false,
                "is_video": false,
                "is_featured_snippet": false,
                "is_malicious": false,
                "is_web_story": false,
                "description": "Feel free to call us with any further questions or for full application. Phone: 760 587 9526. OUR LOCATION. San Diego 92129. OPEN HOURS. Mon-Fri: 8:00am-6:00pm. Read more",
                "pre_snippet": null,
                "extended_snippet": null,
                "images": null,
                "amp_version": false,
                "rating": null,
                "price": null,
                "highlighted": [
                  "San Diego"
                ],
                "links": null,
                "faq": null,
                "extended_people_also_search": null,
                "about_this_result": null,
                "related_result": null,
                "timestamp": null,
                "rectangle": null
              },
              {
                "type": "related_searches",
                "rank_group": 3,
                "rank_absolute": 34,
                "page": 3,
                "position": "left",
                "xpath": "/html[1]/body[1]/div[3]/div[1]/div[12]/div[1]/div[3]/div[1]/div[3]/div[1]/div[1]/div[1]/div[1]/div[2]",
                "items": [
                  "Tiny house san diego for sale",
                  "Tiny house san diego for rent",
                  "Tiny home Community San Diego prices",
                  "Tiny house san diego cost",
                  "Tiny house san diego price",
                  "Used tiny house san diego",
                  "Clever Tiny homes San Diego",
                  "Tiny homes on wheels san diego"
                ],
                "rectangle": null
              }
            ]
          }
        ]
      }
    ]
  }
}